Camunda/Archive/__init__.py
Camunda/Browser/Selenium/__init__.py
Camunda/Calendar/__init__.py
Camunda/Desktop/__init__.py
Camunda/Desktop/OperatingSystem/__init__.py
Camunda/Excel/Application/__init__.py
Camunda/Excel/Files/__init__.py
Camunda/FTP/__init__.py
Camunda/FileSystem/__init__.py
Camunda/HTTP/__init__.py
Camunda/Images/__init__.py
Camunda/JSON/__init__.py
Camunda/JavaAccessBridge/__init__.py
Camunda/MFA/__init__.py
Camunda/MSGraph/__init__.py
Camunda/Outlook/Application/__init__.py
Camunda/PDF/__init__.py
Camunda/SAP/__init__.py
Camunda/Tables/__init__.py
Camunda/Tasks/__init__.py
Camunda/Windows/__init__.py
Camunda/Word/Application/__init__.py
camunda_rpa-1.2.0.dist-info/licenses/LICENSE
camunda_rpa-1.2.0.dist-info/METADATA
camunda_rpa-1.2.0.dist-info/WHEEL
camunda_rpa-1.2.0.dist-info/top_level.txt
camunda_rpa-1.2.0.dist-info/RECORD
